fitdistcp/__init__.py
fitdistcp/evaluate_dmgs_equation.py
fitdistcp/expon.py
fitdistcp/expon_derivs.py
fitdistcp/expon_libs.py
fitdistcp/gamma.py
fitdistcp/gamma_derivs.py
fitdistcp/gamma_libs.py
fitdistcp/genextreme.py
fitdistcp/genextreme_derivs.py
fitdistcp/genextreme_libs.py
fitdistcp/genextreme_p1.py
fitdistcp/genextreme_p12.py
fitdistcp/genextreme_p12_derivs.py
fitdistcp/genextreme_p12_libs.py
fitdistcp/genextreme_p1_derivs.py
fitdistcp/genextreme_p1_libs.py
fitdistcp/genpareto.py
fitdistcp/genpareto_derivs.py
fitdistcp/genpareto_libs.py
fitdistcp/gumbel.py
fitdistcp/gumbel_derivs.py
fitdistcp/gumbel_libs.py
fitdistcp/lnorm.py
fitdistcp/lnorm_derivs.py
fitdistcp/lnorm_libs.py
fitdistcp/norm.py
fitdistcp/norm_derivs.py
fitdistcp/norm_libs.py
fitdistcp/reltest_libs.py
fitdistcp/test.py
fitdistcp/test_example_data.py
fitdistcp/test_gendata.py
fitdistcp/utils.py
fitdistcp/weibull.py
fitdistcp/weibull_derivs.py
fitdistcp/weibull_libs.py
fitdistcp-0.1.1.dist-info/METADATA
fitdistcp-0.1.1.dist-info/WHEEL
fitdistcp-0.1.1.dist-info/licenses/LICENSE.md
fitdistcp-0.1.1.dist-info/RECORD
