Metadata-Version: 2.4
Name: fitdistcp
Version: 0.1.1
Summary: A Python package for making reliable predictions using calibrating priors.
Project-URL: Homepage, https://github.com/lynnejewson/fitdistcp
Author-email: Lynne Jewson <lynne.jewson@gmail.com>
License-Expression: MIT
License-File: LICENSE.md
Classifier: Operating System :: OS Independent
Classifier: Programming Language :: Python :: 3
Requires-Python: >=3.9
Requires-Dist: matplotlib
Requires-Dist: numpy
Requires-Dist: rusampling
Requires-Dist: scikit-learn
Requires-Dist: scipy
